micropython_adxl343/__init__.py
micropython_adxl343/adxl343.py
micropython_adxl343/i2c_helpers.py
micropython_adxl343-0.1.2.dist-info/LICENSE
micropython_adxl343-0.1.2.dist-info/METADATA
micropython_adxl343-0.1.2.dist-info/WHEEL
micropython_adxl343-0.1.2.dist-info/top_level.txt
micropython_adxl343-0.1.2.dist-info/RECORD
