Metadata-Version: 2.1
Name: micropython-adxl343
Version: 0.1.2
Summary: MicroPython Driver for the Analog Devices ADXL343 Accelerometer
Author-email: JDM <xxyx@mailmeto.mozmail.com>
License: MIT
Project-URL: Homepage, https://github.com/jposada202020/MicroPython_ADXL343
Keywords: sensor,micropython,adxl343,tap,double,activity,acceleration,accelerometer,adxl343,gravity,sensor,driver
Classifier: Intended Audience :: Developers
Classifier: Topic :: Software Development :: Libraries
Classifier: Topic :: Software Development :: Embedded Systems
Classifier: Topic :: System :: Hardware
Classifier: License :: OSI Approved :: MIT License
Classifier: Programming Language :: Python :: Implementation :: MicroPython
License-File: LICENSE
